{"stat.killEntity.EntityHorse":4,"stat.leaveGame":7,"stat.killEntity.Blaze":4,"stat.mineBlock.14":50,"stat.mineBlock.13":196,"stat.mineBlock.16":829,"stat.mineBlock.15":365,"stat.mineBlock.18":460,"stat.killEntity.PigZombie":5,"stat.mineBlock.17":64,"stat.entityKilledBy.PigZombie":1,"stat.mineBlock.12":201,"stat.entityKilledBy.Spider":1,"stat.mineBlock.111":5,"achievement.diamonds":4,"stat.mineBlock.114":1,"stat.mineBlock.112":85,"stat.killEntity.Enderman":13,"stat.mineBlock.113":1,"stat.mineBlock.116":1,"achievement.buildPickaxe":16,"stat.killEntity.Witch":3,"achievement.buildBetterPickaxe":16,"achievement.woodenGear":1,"stat.mineBlock.126":3,"achievement.breedCow":16,"stat.mineBlock.175":37,"tconstruct.beginner":8,"achievement.mineWood":88,"stat.useItem.86":2,"stat.useItem.87":19,"stat.useItem.85":2,"achievement.openInventory":1193,"stat.useItem.80":4,"stat.useItem.81":3,"stat.mineBlock.154":1,"stat.mineBlock.152":1,"stat.mineBlock.153":2,"stat.mineBlock.159":1,"achievement.ghast":2,"stat.useItem.98":1,"stat.deaths":12,"stat.playOneMinute":2211718,"stat.mineBlock.172":4,"stat.fishCaught":36,"stat.killEntity.Ghast":2,"stat.fallOneCm":201631,"achievement.killCow":19,"stat.craftItem.1":18,"stat.craftItem.5":328,"stat.treasureFished":1,"stat.killEntity.LavaSlime":5,"achievement.portal":5,"stat.useItem.6":6,"achievement.acquireIron":49,"stat.useItem.1":608,"stat.useItem.4":4170,"stat.useItem.5":21,"stat.useItem.3":1545,"stat.entityKilledBy.Blaze":1,"draconicevolution.dust":3,"stat.useItem.351":14,"stat.craftItem.340":6,"stat.useItem.355":1,"stat.useItem.112":11,"stat.craftItem.101":16,"stat.craftItem.102":16,"stat.useItem.359":8,"stat.craftItem.61":4,"stat.horseOneCm":499322,"stat.craftItem.336":8,"stat.craftItem.339":51,"stat.useItem.361":1,"stat.swimOneCm":382827,"stat.useItem.126":12,"stat.climbOneCm":12433,"tconstruct.pattern":4,"achievement.wrench":1,"achievement.buildWorkBench":2,"achievement.ae2.ChargedQuartz":4,"stat.craftItem.324":1,"stat.craftItem.325":2,"achievement.exploreAllBiomes":{"value":0,"progress":["Sunflower Plains","Birch Forest","Beach","Mesa Plateau","Extreme Hills+","River","Ocean","Taiga","Swampland","Birch Forest Hills","Mesa Plateau F","ForestHills","Mesa","Magical Forest","Flower Forest","Plains","TaigaHills","DesertHills","Stone Beach","Eerie","Forest","Birch Forest Hills M","Desert","Extreme Hills","Hell","Deep Ocean"]},"stat.craftItem.361":4,"stat.craftItem.362":8,"stat.craftItem.364":79,"stat.craftItem.366":20,"stat.craftItem.85":0,"stat.useItem.338":8,"stat.mineBlock.4":2010,"stat.mineBlock.5":36,"stat.junkFished":9,"stat.mineBlock.3":1898,"stat.mineBlock.1":17651,"stat.craftItem.80":4,"stat.craftItem.359":3,"stat.craftItem.350":11,"stat.flyOneCm":736355,"stat.craftItem.351":55,"stat.useItem.101":20,"stat.craftItem.355":1,"stat.craftItem.98":4,"stat.ae2.TurnedCranks":113,"stat.craftItem.346":0,"ic2.mineOre":1099,"stat.killEntity.Bat":1,"stat.craftItem.420":0,"stat.craftItem.301":1,"stat.craftItem.20":108,"ic2.acquireRefinedIron":48,"stat.killEntity.Creeper":40,"stat.killEntity.Blitz":1,"stat.useItem.324":2,"stat.useItem.323":1,"stat.craftItem.35":8,"stat.entityKilledBy.Skeleton":1,"stat.craftItem.33":19,"achievement.buildSword":11,"stat.killEntity.Squid":28,"stat.breakItem.272":1,"stat.craftItem.322":1,"stat.breakItem.274":8,"stat.craftItem.42":2,"stat.craftItem.45":2,"stat.craftItem.44":66,"achievement.killEnemy":294,"achievement.buildFurnace":6,"stat.craftItem.58":2,"stat.drop":495,"stat.craftItem.50":272,"stat.killEntity.Sheep":2,"stat.breakItem.267":1,"stat.craftItem.54":7,"stat.killEntity.Zombie":116,"stat.diveOneCm":199347,"stat.useItem.61":3,"achievement.buildHoe":1,"stat.breakItem.257":1,"stat.mineBlock.81":9,"stat.mineBlock.82":22,"stat.mineBlock.85":3,"stat.mineBlock.87":82,"stat.mineBlock.86":6,"stat.mineBlock.89":44,"stat.mineBlock.88":19,"stat.craftItem.297":65,"stat.jump":12281,"achievement.stoneGear":1,"stat.craftItem.291":1,"stat.craftItem.171":6,"stat.entityKilledBy.CaveSpider":1,"achievement.makeBread":102,"stat.mineBlock.98":8,"stat.useItem.295":462,"stat.useItem.44":88,"achievement.blazeRod":2,"stat.damageTaken":71687,"stat.mineBlock.61":4,"stat.useItem.47":6,"stat.mineBlock.66":2,"stat.useItem.49":6,"stat.useItem.54":17,"stat.killEntity.CaveSpider":4,"stat.useItem.50":257,"stat.entityKilledBy.Zombie":1,"stat.damageDealt":75815,"stat.killEntity.Cow":34,"stat.mineBlock.73":91,"stat.killEntity.Pig":4,"stat.useItem.58":3,"stat.mineBlock.78":72,"stat.useItem.274":1022,"stat.craftItem.261":2,"stat.mineBlock.47":56,"stat.useItem.273":122,"stat.useItem.152":1,"stat.useItem.397":3,"stat.mineBlock.49":37,"stat.useItem.154":1,"stat.walkOneCm":11933408,"stat.craftItem.265":169,"stat.craftItem.386":5,"stat.useItem.278":87,"stat.craftItem.266":1,"stat.craftItem.267":2,"stat.animalsBred":22,"stat.craftItem.388":3,"stat.craftItem.268":1,"stat.craftItem.389":1,"stat.playerKills":4,"stat.craftItem.259":1,"stat.useItem.24":6,"stat.mineBlock.44":3,"stat.mineBlock.58":2,"stat.craftItem.371":25,"stat.craftItem.374":3,"stat.craftItem.256":2,"stat.craftItem.257":2,"stat.mineBlock.101":5,"stat.mineBlock.102":5,"stat.mineBlock.50":45,"stat.useItem.39":5,"stat.mineBlock.107":1,"stat.craftItem.126":12,"stat.mineBlock.54":2,"stat.useItem.291":27,"stat.mineBlock.56":4,"stat.mineBlock.24":7,"stat.killEntity.Skeleton":48,"stat.useItem.257":244,"stat.killEntity.Chicken":56,"stat.craftItem.280":168,"stat.killEntity.Spider":43,"stat.mobKills":460,"stat.mineBlock.21":9,"stat.craftItem.272":3,"stat.craftItem.273":1,"stat.mineBlock.35":9,"stat.mineBlock.38":91,"stat.craftItem.274":8,"stat.useItem.12":8,"stat.mineBlock.37":12,"stat.craftItem.154":1,"stat.useItem.267":692,"stat.mineBlock.39":17,"stat.craftItem.278":0,"stat.useItem.268":28,"stat.useItem.389":4,"stat.craftItem.270":2,"stat.mineBlock.30":61,"achievement.cookFish":2,"stat.useItem.270":5,"stat.useItem.13":12,"stat.useItem.391":427,"stat.mineBlock.32":3,"stat.mineBlock.31":579,"stat.useItem.390":5,"stat.useItem.272":517}